{
  "last_update": "2026-04-10T11:32:59.237497+00:00",
  "source": "CryptoCompare",
  "data": [
    {
      "symbol": "BTC",
      "name": "Bitcoin",
      "current_price": 72170.09,
      "price_change_percentage_24h": 0,
      "high_24h": 73613.4918,
      "low_24h": 70726.68819999999
    },
    {
      "symbol": "ETH",
      "name": "Ethereum",
      "current_price": 2215.28,
      "price_change_percentage_24h": 0,
      "high_24h": 2259.5856000000003,
      "low_24h": 2170.9744
    },
    {
      "symbol": "SOL",
      "name": "Solana",
      "current_price": 83.5,
      "price_change_percentage_24h": 0,
      "high_24h": 85.17,
      "low_24h": 81.83
    }
  ]
}