{
  "last_update": "2026-04-02T19:15:24.337359+00:00",
  "source": "CryptoCompare",
  "data": [
    {
      "symbol": "BTC",
      "name": "Bitcoin",
      "current_price": 67055.32,
      "price_change_percentage_24h": 0,
      "high_24h": 68396.42640000001,
      "low_24h": 65714.2136
    },
    {
      "symbol": "ETH",
      "name": "Ethereum",
      "current_price": 2059.2,
      "price_change_percentage_24h": 0,
      "high_24h": 2100.384,
      "low_24h": 2018.0159999999998
    },
    {
      "symbol": "SOL",
      "name": "Solana",
      "current_price": 79.13,
      "price_change_percentage_24h": 0,
      "high_24h": 80.7126,
      "low_24h": 77.5474
    }
  ]
}